httpayer/__client.py
httpayer/__init__.py
httpayer/client.py
httpayer/constants.py
httpayer/gate.py
httpayer/x402_exact.py
httpayer/_vendor/__init__.py
httpayer/_vendor/x402/__init__.py
httpayer/_vendor/x402/chains.py
httpayer/_vendor/x402/common.py
httpayer/_vendor/x402/encoding.py
httpayer/_vendor/x402/evm_paywall_template.py
httpayer/_vendor/x402/exact.py
httpayer/_vendor/x402/facilitator.py
httpayer/_vendor/x402/networks.py
httpayer/_vendor/x402/path.py
httpayer/_vendor/x402/paywall.py
httpayer/_vendor/x402/py.typed
httpayer/_vendor/x402/svm_paywall_template.py
httpayer/_vendor/x402/types.py
httpayer/_vendor/x402/clients/__init__.py
httpayer/_vendor/x402/clients/base.py
httpayer/_vendor/x402/clients/httpx.py
httpayer/_vendor/x402/clients/requests.py
httpayer/_vendor/x402/fastapi/__init__.py
httpayer/_vendor/x402/fastapi/middleware.py
httpayer/_vendor/x402/flask/__init__.py
httpayer/_vendor/x402/flask/middleware.py
httpayer/x402_solana/__init__.py
httpayer/x402_solana/clients/__init__.py
httpayer/x402_solana/clients/requests.py
httpayer/x402_solana/schemes/exact_svm/__init__.py
httpayer/x402_solana/schemes/exact_svm/client.py
httpayer/x402_solana/shared/svm/__init__.py
httpayer/x402_solana/shared/svm/rpc.py
httpayer/x402_solana/shared/svm/transaction.py
httpayer/x402_solana/shared/svm/wallet.py
httpayer/x402_solana/types/__init__.py
httpayer/x402_solana/types/payment.py
httpayer-0.2.8.dist-info/licenses/LICENSE.md
httpayer-0.2.8.dist-info/METADATA
httpayer-0.2.8.dist-info/WHEEL
httpayer-0.2.8.dist-info/top_level.txt
httpayer-0.2.8.dist-info/RECORD
