Metadata-Version: 2.4
Name: httpayer
Version: 0.2.8
Summary: Python SDK for HTTPayer
Author-email: Brandyn Hamilton <brandyn@httpayer.com>
License: # HTTPayer SDK License Agreement
Requires-Python: >=3.13
License-File: LICENSE.md
Requires-Dist: base58<3.0.0,>=2.1.0
Requires-Dist: httpx<1.0.0,>=0.28.1
Requires-Dist: nest-asyncio<2.0.0,>=1.6.0
Requires-Dist: python-dotenv<2.0.0,>=1.2.0
Requires-Dist: requests<3.0.0,>=2.32.0
Requires-Dist: solders<0.28.0,>=0.27.1
Requires-Dist: web3<8.0.0,>=7.14.0
Dynamic: license-file
